PyDRL/__init__.py
PyDRL-0.0.1.dist-info/METADATA
PyDRL-0.0.1.dist-info/RECORD
PyDRL-0.0.1.dist-info/WHEEL
PyDRL-0.0.1.dist-info/top_level.txt
