Metadata-Version: 2.1
Name: PyDRL
Version: 0.0.1
Summary: A Python Deep Reinforcement Learning library
Home-page: https://github.com/vrishank97/PyDRL
Author: Vrishank Bhardwaj
Author-email: vrishank1997@gmail.com
License: MIT
Platform: UNKNOWN
